prepull_singularity/__init__.py
prepull_singularity-0.2.0.dist-info/LICENSE
prepull_singularity-0.2.0.dist-info/METADATA
prepull_singularity-0.2.0.dist-info/WHEEL
prepull_singularity-0.2.0.dist-info/entry_points.txt
prepull_singularity-0.2.0.dist-info/top_level.txt
prepull_singularity-0.2.0.dist-info/RECORD
