Metadata-Version: 2.1
Name: prepull-singularity
Version: 0.2.0
Summary: A tool for pulling singularity images in HPC environments.
Home-page: https://github.com/biowdl/prepull-singularity
Author: Leiden University Medical Center
Author-email: sasc@lumc.nl
License: MIT
Keywords: singularity pull prepull hpc image container
Platform: UNKNOWN
Classifier: Programming Language :: Python :: 3 :: Only
Classifier: Programming Language :: Python :: 3
Classifier: Programming Language :: Python :: 3.5
Classifier: Programming Language :: Python :: 3.6
Classifier: Programming Language :: Python :: 3.7
Classifier: Programming Language :: Python :: 3.8
Classifier: License :: OSI Approved :: MIT License
Requires-Python: >=3.5
Requires-Dist: pyyaml
Requires-Dist: requests
